{
  "$schema": "../gen/schemas/desktop-schema.json",
  "identifier": "note-window",
  "description": "便签窗口权限(匹配 note-* )",
  "windows": ["note-*"],
  "permissions": [
    "core:default",
    "core:window:allow-set-effects",
    "core:window:allow-start-dragging",
    "core:window:allow-start-resize-dragging",
    "core:window:allow-set-size",
    "core:window:allow-set-position",
    "core:window:allow-set-always-on-top",
    "core:window:allow-close",
    "core:window:allow-destroy",
    "core:window:allow-scale-factor",
    "core:window:allow-outer-size",
    "core:window:allow-outer-position"
  ]
}
